dhademopackage/__init__.py
dhademopackage/demopgm.py
dhademopackage-0.1.dist-info/METADATA
dhademopackage-0.1.dist-info/WHEEL
dhademopackage-0.1.dist-info/top_level.txt
dhademopackage-0.1.dist-info/RECORD
