Metadata-Version: 2.1
Name: dhademopackage
Version: 0.1
Summary: Testing installation of Package
Home-page: UNKNOWN
Author: auth
Author-email: dharunpandian.itss@gmail.com
License: MIT
Platform: UNKNOWN
